tracebackturbo/__init__.py
tracebackturbo/tracebackturbo.py
tracebackturbo-0.3.dist-info/DESCRIPTION.rst
tracebackturbo-0.3.dist-info/METADATA
tracebackturbo-0.3.dist-info/RECORD
tracebackturbo-0.3.dist-info/WHEEL
tracebackturbo-0.3.dist-info/metadata.json
tracebackturbo-0.3.dist-info/top_level.txt
